pandocxnos/__init__.py
pandocxnos/core.py
pandocxnos/main.py
pandocxnos/pandocattributes.py
pandoc_xnos-2.5.0.dist-info/AUTHORS
pandoc_xnos-2.5.0.dist-info/LICENSE
pandoc_xnos-2.5.0.dist-info/METADATA
pandoc_xnos-2.5.0.dist-info/WHEEL
pandoc_xnos-2.5.0.dist-info/entry_points.txt
pandoc_xnos-2.5.0.dist-info/top_level.txt
pandoc_xnos-2.5.0.dist-info/RECORD
